swagger_client/__init__.py
swagger_client/api_client.py
swagger_client/configuration.py
swagger_client/rest.py
swagger_client/api/__init__.py
swagger_client/api/application_data_controller_api.py
swagger_client/api/boundary_aggregate_controller_api.py
swagger_client/api/boundary_owner_mapping_controller_api.py
swagger_client/api/common_model_controller_api.py
swagger_client/api/companies_controller_api.py
swagger_client/api/crops_controller_api.py
swagger_client/api/custom_boundary_controller_api.py
swagger_client/api/entity_audit_collection_controller_api.py
swagger_client/api/farmer_controller_api.py
swagger_client/api/file_controller_api.py
swagger_client/api/generic_o_data_controller_api.py
swagger_client/api/harvest_controller_api.py
swagger_client/api/metrics_master_controller_api.py
swagger_client/api/ml_metrics_aggregate_controller_api.py
swagger_client/api/notes_controller_api.py
swagger_client/api/notifications_controller_api.py
swagger_client/api/plot_upload_history_controller_api.py
swagger_client/api/report_generation_controller_api.py
swagger_client/api/report_history_controller_api.py
swagger_client/api/satellite_catalogue_controller_api.py
swagger_client/api/seeding_controller_api.py
swagger_client/api/system_boundary_controller_api.py
swagger_client/api/tillage_controller_api.py
swagger_client/api/weather_data_controller_api.py
swagger_client/api/yield_data_controller_api.py
swagger_client/models/__init__.py
swagger_client/models/application_data_product_details.py
swagger_client/models/application_data_request.py
swagger_client/models/application_data_response.py
swagger_client/models/boundary_mapping_request.py
swagger_client/models/boundary_owner_mapping_request.py
swagger_client/models/boundary_owner_mapping_response.py
swagger_client/models/boundary_request.py
swagger_client/models/boundary_response.py
swagger_client/models/common_model_request.py
swagger_client/models/common_model_response.py
swagger_client/models/company_request.py
insights_client_test-1.0.0.dist-info/METADATA
insights_client_test-1.0.0.dist-info/WHEEL
insights_client_test-1.0.0.dist-info/top_level.txt
insights_client_test-1.0.0.dist-info/RECORD
